mux_io/VHDL/mux_8_bit.vhd
library ieee;
use ieee.std_logic_1164.all;

entity mux_8_bit is
    port (
        s : in  std_logic;
        A : in  std_logic_vector(7 downto 0);
        B : in  std_logic_vector(7 downto 0);
        Q : out std_logic_vector(7 downto 0)
    );
end entity mux_8_bit;

architecture rtl of mux_8_bit is
begin
    Q   <=  A when s = '0' else 
        <=  B when s = '1' else
        (others =>'0');
end architecture rtl;

mux_io/VHDL/tb_ex01.vhd
library ieee;
use ieee.std_logic_1164.all;
use std.textio.all;
use ieee.std_logic_textio.all;

entity tb_ex01 is
end entity tb_ex01;

architecture behavioural of tb_ex01 is
    -- Testbench stimulus and observation signals.
    signal A    : std_logic_vector(7 downto 0)  := (others=>'0');
    signal B    : std_logic_vector(7 downto 0)  := (others=>'0');
    signal s    : std_logic                     := '0';
    signal Q    : std_logic_vector(7 downto 0);
begin
    -- MUX
    dut: entity work.mux_8_bit(rtl)
    port map(
        A => A,
        B => B,
        s => s,
        Q => Q
    );


    stimulus: process
        file input_file     :   TEXT open READ_MODE is "input";
        file output_file    :   TEXT open WRITE_MODE is "output";

        -- line variable and data variable
        variable current_line   :   LINE;
        variable output_line    :   LINE;
        variable vector_data    :   std_logic_vector(16 downto  0);
        variable good           :   boolean;
        variable ln             :   integer := 0;

    begin
        report "Starting stimulus process";
        while not endfile(input_file) loop
            readline(input_file, current_line);
            ln := ln + 1;

            read (current_line, vector_data, good); 
            assert good report "Bad input format at line " & integer'image(ln) severity error;
            if not good then
                next;
            end if;

            A   <=  vector_data(16 downto 9);
            B   <=  vector_data(8 downto 1);
            s   <=  vector_data(0);
            wait for 10 ns;
            write(output_line, Q);
            writeline(output_file, output_line);
        end loop;
        report "End of stimulus";
        file_close(input_file);
        file_close(output_file);
        wait;
    end process;


end architecture behavioural;

mux_io/VHDL/wave.vcd
$date
  Tue Mar  3 19:00:28 2026
$end
$version
  GHDL v0
$end
$timescale
  1 fs
$end
$scope module standard $end
$upscope $end
$scope module textio $end
$upscope $end
$scope module std_logic_1164 $end
$upscope $end
$scope module std_logic_textio $end
$upscope $end
$scope module tb_ex01 $end
$var reg 8 ! a[7:0] $end
$var reg 8 " b[7:0] $end
$var reg 1 # s $end
$var reg 8 $ q[7:0] $end
$scope module dut $end
$var reg 1 % s $end
$var reg 8 & a[7:0] $end
$var reg 8 ' b[7:0] $end
$var reg 8 ( q[7:0] $end
$upscope $end
$upscope $end
$enddefinitions $end
#0
b00001101 !
b10110010 "
0#
b00001101 $
0%
b00001101 &
b10110010 '
b00001101 (
#10000000
1#
b10110010 $
1%
b10110010 (
#20000000
b11001010 !
b01011011 "
0#
b11001010 $
0%
b11001010 &
b01011011 '
b11001010 (
#30000000
1#
b01011011 $
1%
b01011011 (
#40000000
b11111111 !
b00000000 "
0#
b11111111 $
0%
b11111111 &
b00000000 '
b11111111 (
#50000000
1#
b00000000 $
1%
b00000000 (
#60000000
b00000000 !
b11111111 "
0#
0%
b00000000 &
b11111111 '
#70000000
1#
b11111111 $
1%
b11111111 (
